aspose/__init__.py
aspose/pdf.cpython-310-x86_64-linux-gnu.so
aspose/pdf.cpython-311-x86_64-linux-gnu.so
aspose/pdf.cpython-312-x86_64-linux-gnu.so
aspose/pdf.cpython-313-x86_64-linux-gnu.so
aspose/pdf.cpython-39-x86_64-linux-gnu.so
aspose/pycore.cpython-310-x86_64-linux-gnu.so
aspose/pycore.cpython-311-x86_64-linux-gnu.so
aspose/pycore.cpython-312-x86_64-linux-gnu.so
aspose/pycore.cpython-313-x86_64-linux-gnu.so
aspose/pycore.cpython-39-x86_64-linux-gnu.so
aspose/pydrawing.cpython-310-x86_64-linux-gnu.so
aspose/pydrawing.cpython-311-x86_64-linux-gnu.so
aspose/pydrawing.cpython-312-x86_64-linux-gnu.so
aspose/pydrawing.cpython-313-x86_64-linux-gnu.so
aspose/pydrawing.cpython-39-x86_64-linux-gnu.so
aspose/pygc.cpython-310-x86_64-linux-gnu.so
aspose/pygc.cpython-311-x86_64-linux-gnu.so
aspose/pygc.cpython-312-x86_64-linux-gnu.so
aspose/pygc.cpython-313-x86_64-linux-gnu.so
aspose/pygc.cpython-39-x86_64-linux-gnu.so
aspose/pyreflection.cpython-310-x86_64-linux-gnu.so
aspose/pyreflection.cpython-311-x86_64-linux-gnu.so
aspose/pyreflection.cpython-312-x86_64-linux-gnu.so
aspose/pyreflection.cpython-313-x86_64-linux-gnu.so
aspose/pyreflection.cpython-39-x86_64-linux-gnu.so
aspose/__pyinstaller/__init__.pyi
aspose/__pyinstaller/hook-aspose.py
aspose/assemblies/pdf/Aspose.PDF.dll
aspose/assemblies/pdf/Microsoft.Bcl.AsyncInterfaces.dll
aspose/assemblies/pdf/Microsoft.DotNet.PlatformAbstractions.dll
aspose/assemblies/pdf/Microsoft.Extensions.DependencyModel.dll
aspose/assemblies/pdf/Microsoft.Extensions.Logging.Abstractions.dll
aspose/assemblies/pdf/Microsoft.Win32.SystemEvents.dll
aspose/assemblies/pdf/Newtonsoft.Json.dll
aspose/assemblies/pdf/System.Configuration.ConfigurationManager.dll
aspose/assemblies/pdf/System.Diagnostics.DiagnosticSource.dll
aspose/assemblies/pdf/System.Diagnostics.PerformanceCounter.dll
aspose/assemblies/pdf/System.Drawing.Common.dll
aspose/assemblies/pdf/System.Formats.Asn1.dll
aspose/assemblies/pdf/System.Net.Http.Json.dll
aspose_pdf-25.12.0.dist-info/METADATA
aspose_pdf-25.12.0.dist-info/WHEEL
aspose_pdf-25.12.0.dist-info/entry_points.txt
aspose_pdf-25.12.0.dist-info/top_level.txt
aspose_pdf-25.12.0.dist-info/RECORD
