Metadata-Version: 2.1
Name: aspose-pdf
Version: 25.12.0
Summary: Aspose.PDF for Python via .NET is a wrapper for Python to perform document management can easily be used to generate, modify, convert, render, secure and print documents without using Adobe Acrobat.
Home-page: https://products.aspose.com/pdf/python-net/
Author: Aspose
License: Other/Proprietary License
Project-URL: Blog, https://blog.aspose.com/categories/aspose.pdf-product-family/
Project-URL: Demos, https://products.aspose.app/pdf/family
Project-URL: Docs, https://docs.aspose.com/pdf/python-net/
Project-URL: Examples, https://github.com/aspose-pdf/Aspose.PDF-for-Python-via-.NET/
Project-URL: Free Support, https://forum.aspose.com/c/pdf
Project-URL: API Reference, https://reference.aspose.com/pdf/python-net/
Project-URL: Release Notes, https://releases.aspose.com/pdf/pythonnet/release-notes/
Project-URL: Temporary License, https://purchase.aspose.com/temporary-license
Keywords: Aspose.PDF,PDF,XFA,XPS,TIFF,PCL,SVG,HTML,XML,XSL-FO,FDF,XFDF,PDF/A,form,Portfolio,EPUB,PSD,to,XLS,PDF-to-DOC
Platform: linux_x86_64
Classifier: Development Status :: 5 - Production/Stable
Classifier: Intended Audience :: Developers
Classifier: Intended Audience :: Education
Classifier: License :: Other/Proprietary License
Classifier: Operating System :: MacOS :: MacOS X
Classifier: Operating System :: Microsoft :: Windows
Classifier: Operating System :: POSIX :: Linux
Classifier: Operating System :: Unix
Classifier: Programming Language :: Python :: 3 :: Only
Classifier: Programming Language :: Python :: 3.9
Classifier: Programming Language :: Python :: 3.10
Classifier: Programming Language :: Python :: 3.11
Classifier: Programming Language :: Python :: 3.12
Classifier: Programming Language :: Python :: 3.13
Classifier: Topic :: Software Development
Classifier: Topic :: Software Development :: Libraries
Classifier: Topic :: Office/Business
Classifier: Topic :: Office/Business :: Office Suites
Requires-Python: >=3.9,<3.14
